duots/__init__.py
duots/compose.py
duots/filter_select.py
duots/generate.py
duots/process.py
duots/calculators/__init__.py
duots/calculators/double.py
duots/calculators/features.py
duots/calculators/single.py
duots/segment/__init__.py
duots/segment/double.py
duots/segment/single.py
duots/transform/__init__.py
duots/transform/double.py
duots/transform/single.py
duots-0.1.10.dist-info/licenses/LICENSE
duots-0.1.10.dist-info/METADATA
duots-0.1.10.dist-info/WHEEL
duots-0.1.10.dist-info/top_level.txt
duots-0.1.10.dist-info/RECORD
