Metadata-Version: 2.4
Name: duots
Version: 0.1.10
Summary: Composable timeseries feature extraction for paired signals.
Author-email: J Mifsud <jmifsud@posteo.net>
Project-URL: Homepage, https://github.com/4d30/duots
Project-URL: Repository, https://github.com/4d30/duots
Project-URL: Issues, https://github.com/4d30/duots/issues
Requires-Python: >=3.11
License-File: LICENSE
Requires-Dist: scipy>=1.8
Requires-Dist: more-itertools>=10.7.0
Provides-Extra: gpu
Requires-Dist: sampen-gpu; extra == "gpu"
Dynamic: license-file
